doodle/__init__.py
doodle/manual.py
doodle-0.1.dist-info/DESCRIPTION.rst
doodle-0.1.dist-info/METADATA
doodle-0.1.dist-info/RECORD
doodle-0.1.dist-info/WHEEL
doodle-0.1.dist-info/metadata.json
doodle-0.1.dist-info/top_level.txt
