Metadata-Version: 2.0
Name: doodle
Version: 0.1
Summary: A library to segment objects in an image in a semi-automated fashion.
Home-page: https://github.com/pskeshu/doodle
Author: Kesavan Subburam
Author-email: pskesavan@tifrh.res.in
License: MIT
Platform: UNKNOWN
Requires-Dist: matplotlib (>=2.0.0)
Requires-Dist: numpy (>=1.12.1)
Requires-Dist: scikit-image (>=0.13.0)
